doc/conf.py
doc/examples.rst
doc/index.rst
doc/make.py
doc/_static/contents.png
doc/_static/file.png
doc/_static/mpl.css
doc/_static/navigation.png
doc/_static/region_ds9.jpg
doc/_static/region_mpl.png
doc/_templates/indexsidebar.html
doc/_templates/layout.html
doc/api/index.rst
doc/figures/demo_filter_mask.py
doc/figures/pspc_skyview.fits
doc/figures/test.reg
doc/figures/test02.reg
doc/figures/test_region_drawing.py
doc/figures/test_region_drawing2.py
doc/sphinxext/github_sphinx.py
doc/sphinxext/plot_directive_v3.py
doc/users/index.rst
doc/users/installing.rst
doc/users/overview.rst
examples/demo_helper.py
examples/demo_print_region.py
examples/demo_region01.py
examples/demo_region02.py
examples/demo_region03.py
examples/demo_region04.py
examples/demo_region_filter01.py
examples/sample_fits01.header
examples/sample_fits02.header
examples/test.header
examples/test.reg
examples/test01.reg
examples/test01_ciao.reg
examples/test01_ciao_physical.reg
examples/test01_ds9_physical.reg
examples/test01_fk5.reg
examples/test01_fk5_degree.reg
examples/test01_fk5_sexagecimal.reg
examples/test01_gal.reg
examples/test01_img.reg
examples/test01_mixed.reg
examples/test01_print.reg
examples/test02.reg
examples/test04_img.reg
examples/test_annuli.reg
examples/test_annuli_ciao.reg
examples/test_annuli_wcs.reg
examples/test_context.reg
examples/test_text.reg
src/_region_filter.c
src/_region_filter.pyx
src/c_numpy.pxd
src/c_python.pxd
src/geom.h
stregion/__init__.py
stregion/_region_filter.cp311-win32.pyd
stregion/ds9_attr_parser.py
stregion/ds9_region_parser.py
stregion/kapteyn_celestial.py
stregion/mpl_helper.py
stregion/parser_helper.py
stregion/physical_coordinate.py
stregion/region_numbers.py
stregion/region_to_filter.py
stregion/version.py
stregion/wcs_converter.py
stregion/wcs_helper.py
stregion-1.1.12.dist-info/licenses/LICENSE.txt
stregion-1.1.12.dist-info/licenses/LICENSE_kapteyn.txt
tests/test_region.py
tests/test_wcs_helper.py
stregion-1.1.12.dist-info/METADATA
stregion-1.1.12.dist-info/WHEEL
stregion-1.1.12.dist-info/top_level.txt
stregion-1.1.12.dist-info/RECORD
