Metadata-Version: 2.4
Name: stregion
Version: 1.1.12
Summary: python parser for ds9 region files
Author-email: Jae-Joon Lee <lee.j.joon@gmail.com>
License: Copyright (c) 2009 Jae-Joon Lee
Project-URL: repository, http://github.com/spacetelescope/stregion
Project-URL: download, http://github.com/spacetelescope/stregion/releases
Classifier: Development Status :: 5 - Production/Stable
Classifier: Intended Audience :: Science/Research
Classifier: License :: OSI Approved :: MIT License
Classifier: Operating System :: MacOS :: MacOS X
Classifier: Operating System :: POSIX :: Linux
Classifier: Programming Language :: Cython
Classifier: Programming Language :: Python
Classifier: Programming Language :: Python :: 3
Classifier: Topic :: Scientific/Engineering :: Astronomy
Requires-Python: >=3.9
License-File: LICENSE.txt
License-File: LICENSE_kapteyn.txt
Requires-Dist: numpy
Requires-Dist: pyparsing>=3.0.0
Dynamic: license-file
